sht3x/__init__.py
sht3x/sht3x.py
sht3x-0.0.5.dist-info/LICENSE
sht3x-0.0.5.dist-info/METADATA
sht3x-0.0.5.dist-info/WHEEL
sht3x-0.0.5.dist-info/top_level.txt
sht3x-0.0.5.dist-info/RECORD
